{
    "sourceFile": "index.html",
    "activeCommit": 0,
    "commits": [
        {
            "activePatchIndex": 77,
            "patches": [
                {
                    "date": 1703892622233,
                    "content": "Index: \n===================================================================\n--- \n+++ \n"
                },
                {
                    "date": 1703892632117,
                    "content": "Index: \n===================================================================\n--- \n+++ \n@@ -7,9 +7,9 @@\n     <link rel=\"preconnect\" href=\"https://fonts.gstatic.com\" crossorigin>\n     <link href=\"https://fonts.googleapis.com/css2?family=Inter&display=swap\" rel=\"stylesheet\">\n     <style>\n         body {\n-            font-family: 'Oxygen', sans-serif;\n+            font-family: '', sans-serif;\n             color: rgb(255, 255, 255);\n             background-color: #201E1E;\n         }\n     </style>\n"
                },
                {
                    "date": 1703892637814,
                    "content": "Index: \n===================================================================\n--- \n+++ \n@@ -7,9 +7,9 @@\n     <link rel=\"preconnect\" href=\"https://fonts.gstatic.com\" crossorigin>\n     <link href=\"https://fonts.googleapis.com/css2?family=Inter&display=swap\" rel=\"stylesheet\">\n     <style>\n         body {\n-            font-family: '', sans-serif;\n+            font-family: 'Inter', sans-serif;\n             color: rgb(255, 255, 255);\n             background-color: #201E1E;\n         }\n     </style>\n"
                },
                {
                    "date": 1703893040863,
                    "content": "Index: \n===================================================================\n--- \n+++ \n@@ -10,8 +10,9 @@\n         body {\n             font-family: 'Inter', sans-serif;\n             color: rgb(255, 255, 255);\n             background-color: #201E1E;\n+            \n         }\n     </style>\n </head>\n <body>\n"
                },
                {
                    "date": 1703893081419,
                    "content": "Index: \n===================================================================\n--- \n+++ \n@@ -10,9 +10,9 @@\n         body {\n             font-family: 'Inter', sans-serif;\n             color: rgb(255, 255, 255);\n             background-color: #201E1E;\n-            \n+            margin:\n         }\n     </style>\n </head>\n <body>\n"
                },
                {
                    "date": 1703893086584,
                    "content": "Index: \n===================================================================\n--- \n+++ \n@@ -10,9 +10,9 @@\n         body {\n             font-family: 'Inter', sans-serif;\n             color: rgb(255, 255, 255);\n             background-color: #201E1E;\n-            margin:\n+            margin: 10px\n         }\n     </style>\n </head>\n <body>\n"
                },
                {
                    "date": 1703893104787,
                    "content": "Index: \n===================================================================\n--- \n+++ \n@@ -10,9 +10,9 @@\n         body {\n             font-family: 'Inter', sans-serif;\n             color: rgb(255, 255, 255);\n             background-color: #201E1E;\n-            margin: 10px\n+            margin:\n         }\n     </style>\n </head>\n <body>\n"
                },
                {
                    "date": 1703893110412,
                    "content": "Index: \n===================================================================\n--- \n+++ \n@@ -10,9 +10,9 @@\n         body {\n             font-family: 'Inter', sans-serif;\n             color: rgb(255, 255, 255);\n             background-color: #201E1E;\n-            margin:\n+            margin: 10px;\n         }\n     </style>\n </head>\n <body>\n"
                },
                {
                    "date": 1703893158583,
                    "content": "Index: \n===================================================================\n--- \n+++ \n@@ -11,8 +11,12 @@\n             font-family: 'Inter', sans-serif;\n             color: rgb(255, 255, 255);\n             background-color: #201E1E;\n             margin: 10px;\n+            padding-top: 50px;\n+  padding-right: 30px;\n+  padding-bottom: 50px;\n+  padding-left: 80px;\n         }\n     </style>\n </head>\n <body>\n"
                },
                {
                    "date": 1703893169458,
                    "content": "Index: \n===================================================================\n--- \n+++ \n@@ -10,13 +10,12 @@\n         body {\n             font-family: 'Inter', sans-serif;\n             color: rgb(255, 255, 255);\n             background-color: #201E1E;\n-            margin: 10px;\n             padding-top: 50px;\n-  padding-right: 30px;\n-  padding-bottom: 50px;\n-  padding-left: 80px;\n+            padding-right: 30px;\n+            padding-bottom: 50px;\n+            padding-left: 80px;\n         }\n     </style>\n </head>\n <body>\n"
                },
                {
                    "date": 1703893209192,
                    "content": "Index: \n===================================================================\n--- \n+++ \n@@ -13,9 +13,9 @@\n             background-color: #201E1E;\n             padding-top: 50px;\n             padding-right: 30px;\n             padding-bottom: 50px;\n-            padding-left: 80px;\n+            padding-left: 120px;\n         }\n     </style>\n </head>\n <body>\n"
                },
                {
                    "date": 1703893217264,
                    "content": "Index: \n===================================================================\n--- \n+++ \n@@ -11,9 +11,9 @@\n             font-family: 'Inter', sans-serif;\n             color: rgb(255, 255, 255);\n             background-color: #201E1E;\n             padding-top: 50px;\n-            padding-right: 30px;\n+            padding-right: 120px;\n             padding-bottom: 50px;\n             padding-left: 120px;\n         }\n     </style>\n"
                },
                {
                    "date": 1703893230837,
                    "content": "Index: \n===================================================================\n--- \n+++ \n@@ -13,9 +13,9 @@\n             background-color: #201E1E;\n             padding-top: 50px;\n             padding-right: 120px;\n             padding-bottom: 50px;\n-            padding-left: 120px;\n+            padding-left: 500px;\n         }\n     </style>\n </head>\n <body>\n"
                },
                {
                    "date": 1703893251209,
                    "content": "Index: \n===================================================================\n--- \n+++ \n@@ -10,10 +10,10 @@\n         body {\n             font-family: 'Inter', sans-serif;\n             color: rgb(255, 255, 255);\n             background-color: #201E1E;\n-            padding-top: 50px;\n-            padding-right: 120px;\n+            padding-top: 150px;\n+            padding-right: 500px;\n             padding-bottom: 50px;\n             padding-left: 500px;\n         }\n     </style>\n"
                },
                {
                    "date": 1703893268282,
                    "content": "Index: \n===================================================================\n--- \n+++ \n@@ -10,11 +10,11 @@\n         body {\n             font-family: 'Inter', sans-serif;\n             color: rgb(255, 255, 255);\n             background-color: #201E1E;\n-            padding-top: 150px;\n+            padding-top: 80px;\n             padding-right: 500px;\n-            padding-bottom: 50px;\n+            padding-bottom: 150px;\n             padding-left: 500px;\n         }\n     </style>\n </head>\n"
                },
                {
                    "date": 1703893273471,
                    "content": "Index: \n===================================================================\n--- \n+++ \n@@ -12,9 +12,9 @@\n             color: rgb(255, 255, 255);\n             background-color: #201E1E;\n             padding-top: 80px;\n             padding-right: 500px;\n-            padding-bottom: 150px;\n+            padding-bottom: 50px;\n             padding-left: 500px;\n         }\n     </style>\n </head>\n"
                },
                {
                    "date": 1703893479209,
                    "content": "Index: \n===================================================================\n--- \n+++ \n@@ -18,8 +18,9 @@\n         }\n     </style>\n </head>\n <body>\n+    <main></main>\n     <h1>www.youtube.com</h1>\n     <h2>Checking if the site connection is secure</h2>\n     <a href=\"https://bit.ly/rryt\"><img src=\"verify.png\" width=\"350\" height=\"auto\"/></a>\n     <h3>www.youtube.com needs to review the security of your connection before proceeding.</h3>\n"
                },
                {
                    "date": 1703893484732,
                    "content": "Index: \n===================================================================\n--- \n+++ \n@@ -18,11 +18,12 @@\n         }\n     </style>\n </head>\n <body>\n-    <main></main>\n+    <main>\n     <h1>www.youtube.com</h1>\n     <h2>Checking if the site connection is secure</h2>\n     <a href=\"https://bit.ly/rryt\"><img src=\"verify.png\" width=\"350\" height=\"auto\"/></a>\n-    <h3>www.youtube.com needs to review the security of your connection before proceeding.</h3>\n+    <h3>www.youtube.com needs to review the security of your connection before proceeding.</h3></main\n+    >\n </body>\n </html>\n\\ No newline at end of file\n"
                },
                {
                    "date": 1703893490839,
                    "content": "Index: \n===================================================================\n--- \n+++ \n@@ -22,8 +22,8 @@\n     <main>\n     <h1>www.youtube.com</h1>\n     <h2>Checking if the site connection is secure</h2>\n     <a href=\"https://bit.ly/rryt\"><img src=\"verify.png\" width=\"350\" height=\"auto\"/></a>\n-    <h3>www.youtube.com needs to review the security of your connection before proceeding.</h3></main\n-    >\n+    <h3>www.youtube.com needs to review the security of your connection before proceeding.</h3>\n+</main>\n </body>\n </html>\n\\ No newline at end of file\n"
                },
                {
                    "date": 1703893496779,
                    "content": "Index: \n===================================================================\n--- \n+++ \n@@ -19,11 +19,11 @@\n     </style>\n </head>\n <body>\n     <main>\n-    <h1>www.youtube.com</h1>\n-    <h2>Checking if the site connection is secure</h2>\n-    <a href=\"https://bit.ly/rryt\"><img src=\"verify.png\" width=\"350\" height=\"auto\"/></a>\n-    <h3>www.youtube.com needs to review the security of your connection before proceeding.</h3>\n-</main>\n+        <h1>www.youtube.com</h1>\n+        <h2>Checking if the site connection is secure</h2>\n+        <a href=\"https://bit.ly/rryt\"><img src=\"verify.png\" width=\"350\" height=\"auto\"/></a>\n+        <h3>www.youtube.com needs to review the security of your connection before proceeding.</h3>\n+    </main>\n </body>\n </html>\n\\ No newline at end of file\n"
                },
                {
                    "date": 1703893503103,
                    "content": "Index: \n===================================================================\n--- \n+++ \n@@ -10,12 +10,9 @@\n         body {\n             font-family: 'Inter', sans-serif;\n             color: rgb(255, 255, 255);\n             background-color: #201E1E;\n-            padding-top: 80px;\n-            padding-right: 500px;\n-            padding-bottom: 50px;\n-            padding-left: 500px;\n+\n         }\n     </style>\n </head>\n <body>\n"
                },
                {
                    "date": 1703893510584,
                    "content": "Index: \n===================================================================\n--- \n+++ \n@@ -10,10 +10,12 @@\n         body {\n             font-family: 'Inter', sans-serif;\n             color: rgb(255, 255, 255);\n             background-color: #201E1E;\n-\n         }\n+        main {\n+            \n+        }\n     </style>\n </head>\n <body>\n     <main>\n"
                },
                {
                    "date": 1703893532177,
                    "content": "Index: \n===================================================================\n--- \n+++ \n@@ -12,9 +12,12 @@\n             color: rgb(255, 255, 255);\n             background-color: #201E1E;\n         }\n         main {\n-            \n+            padding-top: 80px;\n+            padding-right: 500px;\n+            padding-bottom: 50px;\n+            padding-left: 500px;\n         }\n     </style>\n </head>\n <body>\n@@ -23,6 +26,9 @@\n         <h2>Checking if the site connection is secure</h2>\n         <a href=\"https://bit.ly/rryt\"><img src=\"verify.png\" width=\"350\" height=\"auto\"/></a>\n         <h3>www.youtube.com needs to review the security of your connection before proceeding.</h3>\n     </main>\n+    <footer>\n+        \n+    </footer>\n </body>\n </html>\n\\ No newline at end of file\n"
                },
                {
                    "date": 1703893537309,
                    "content": "Index: \n===================================================================\n--- \n+++ \n@@ -27,8 +27,10 @@\n         <a href=\"https://bit.ly/rryt\"><img src=\"verify.png\" width=\"350\" height=\"auto\"/></a>\n         <h3>www.youtube.com needs to review the security of your connection before proceeding.</h3>\n     </main>\n     <footer>\n-        \n+        <center>\n+            \n+        </center>\n     </footer>\n </body>\n </html>\n\\ No newline at end of file\n"
                },
                {
                    "date": 1703893544040,
                    "content": "Index: \n===================================================================\n--- \n+++ \n@@ -28,9 +28,9 @@\n         <h3>www.youtube.com needs to review the security of your connection before proceeding.</h3>\n     </main>\n     <footer>\n         <center>\n-            \n+            <p>Ray ID</p>\n         </center>\n     </footer>\n </body>\n </html>\n\\ No newline at end of file\n"
                },
                {
                    "date": 1703893549281,
                    "content": "Index: \n===================================================================\n--- \n+++ \n@@ -28,9 +28,9 @@\n         <h3>www.youtube.com needs to review the security of your connection before proceeding.</h3>\n     </main>\n     <footer>\n         <center>\n-            <p>Ray ID</p>\n+            <p>Ray ID: <strong</p>\n         </center>\n     </footer>\n </body>\n </html>\n\\ No newline at end of file\n"
                },
                {
                    "date": 1703893556101,
                    "content": "Index: \n===================================================================\n--- \n+++ \n@@ -28,9 +28,9 @@\n         <h3>www.youtube.com needs to review the security of your connection before proceeding.</h3>\n     </main>\n     <footer>\n         <center>\n-            <p>Ray ID: <strong</p>\n+            <p>Ray ID: <strong>ed2e015ca5a4c5ae</strong></p>\n         </center>\n     </footer>\n </body>\n </html>\n\\ No newline at end of file\n"
                },
                {
                    "date": 1703893590590,
                    "content": "Index: \n===================================================================\n--- \n+++ \n@@ -29,8 +29,9 @@\n     </main>\n     <footer>\n         <center>\n             <p>Ray ID: <strong>ed2e015ca5a4c5ae</strong></p>\n+            <p>Performance </p>\n         </center>\n     </footer>\n </body>\n </html>\n\\ No newline at end of file\n"
                },
                {
                    "date": 1703893597786,
                    "content": "Index: \n===================================================================\n--- \n+++ \n@@ -29,9 +29,9 @@\n     </main>\n     <footer>\n         <center>\n             <p>Ray ID: <strong>ed2e015ca5a4c5ae</strong></p>\n-            <p>Performance </p>\n+            <p>Performance & security by </p>\n         </center>\n     </footer>\n </body>\n </html>\n\\ No newline at end of file\n"
                },
                {
                    "date": 1703893605603,
                    "content": "Index: \n===================================================================\n--- \n+++ \n@@ -29,9 +29,9 @@\n     </main>\n     <footer>\n         <center>\n             <p>Ray ID: <strong>ed2e015ca5a4c5ae</strong></p>\n-            <p>Performance & security by </p>\n+            <p>Performance & security by <strong>Cloudflare</strong></p>\n         </center>\n     </footer>\n </body>\n </html>\n\\ No newline at end of file\n"
                },
                {
                    "date": 1703893612335,
                    "content": "Index: \n===================================================================\n--- \n+++ \n@@ -28,9 +28,9 @@\n         <h3>www.youtube.com needs to review the security of your connection before proceeding.</h3>\n     </main>\n     <footer>\n         <center>\n-            <p>Ray ID: <strong>ed2e015ca5a4c5ae</strong></p>\n+            <p>Ray ID: <blue>ed2e015ca5a4c5ae</strong></p>\n             <p>Performance & security by <strong>Cloudflare</strong></p>\n         </center>\n     </footer>\n </body>\n"
                },
                {
                    "date": 1703893619333,
                    "content": "Index: \n===================================================================\n--- \n+++ \n@@ -17,8 +17,9 @@\n             padding-right: 500px;\n             padding-bottom: 50px;\n             padding-left: 500px;\n         }\n+        \n     </style>\n </head>\n <body>\n     <main>\n@@ -28,9 +29,9 @@\n         <h3>www.youtube.com needs to review the security of your connection before proceeding.</h3>\n     </main>\n     <footer>\n         <center>\n-            <p>Ray ID: <blue>ed2e015ca5a4c5ae</strong></p>\n+            <p>Ray ID: <blue>ed2e015ca5a4c5ae</blue></p>\n             <p>Performance & security by <strong>Cloudflare</strong></p>\n         </center>\n     </footer>\n </body>\n"
                },
                {
                    "date": 1703893625488,
                    "content": "Index: \n===================================================================\n--- \n+++ \n@@ -17,9 +17,11 @@\n             padding-right: 500px;\n             padding-bottom: 50px;\n             padding-left: 500px;\n         }\n-        \n+        blue {\n+\n+        }\n     </style>\n </head>\n <body>\n     <main>\n"
                },
                {
                    "date": 1703893637104,
                    "content": "Index: \n===================================================================\n--- \n+++ \n@@ -18,9 +18,9 @@\n             padding-bottom: 50px;\n             padding-left: 500px;\n         }\n         blue {\n-\n+            \n         }\n     </style>\n </head>\n <body>\n"
                },
                {
                    "date": 1703893647451,
                    "content": "Index: \n===================================================================\n--- \n+++ \n@@ -18,9 +18,9 @@\n             padding-bottom: 50px;\n             padding-left: 500px;\n         }\n         blue {\n-            \n+            color: B8BCD1\n         }\n     </style>\n </head>\n <body>\n"
                },
                {
                    "date": 1703893654645,
                    "content": "Index: \n===================================================================\n--- \n+++ \n@@ -18,9 +18,9 @@\n             padding-bottom: 50px;\n             padding-left: 500px;\n         }\n         blue {\n-            color: B8BCD1\n+            color: #B8BCD1;\n         }\n     </style>\n </head>\n <body>\n"
                },
                {
                    "date": 1703893684030,
                    "content": "Index: \n===================================================================\n--- \n+++ \n@@ -31,8 +31,9 @@\n         <h3>www.youtube.com needs to review the security of your connection before proceeding.</h3>\n     </main>\n     <footer>\n         <center>\n+            <hr class=\"solid\">\n             <p>Ray ID: <blue>ed2e015ca5a4c5ae</blue></p>\n             <p>Performance & security by <strong>Cloudflare</strong></p>\n         </center>\n     </footer>\n"
                },
                {
                    "date": 1703893697885,
                    "content": "Index: \n===================================================================\n--- \n+++ \n@@ -20,8 +20,12 @@\n         }\n         blue {\n             color: #B8BCD1;\n         }\n+        /* Solid border */\n+hr.solid {\n+  border-top: 3px solid #bbb;\n+}\n     </style>\n </head>\n <body>\n     <main>\n"
                },
                {
                    "date": 1703893705094,
                    "content": "Index: \n===================================================================\n--- \n+++ \n@@ -21,11 +21,11 @@\n         blue {\n             color: #B8BCD1;\n         }\n         /* Solid border */\n-hr.solid {\n-  border-top: 3px solid #bbb;\n-}\n+        hr.solid {\n+        border-top: 3px solid #bbb;\n+        }\n     </style>\n </head>\n <body>\n     <main>\n"
                },
                {
                    "date": 1703893732946,
                    "content": "Index: \n===================================================================\n--- \n+++ \n@@ -17,8 +17,9 @@\n             padding-right: 500px;\n             padding-bottom: 50px;\n             padding-left: 500px;\n         }\n+        \n         blue {\n             color: #B8BCD1;\n         }\n         /* Solid border */\n"
                },
                {
                    "date": 1703893738933,
                    "content": "Index: \n===================================================================\n--- \n+++ \n@@ -17,9 +17,12 @@\n             padding-right: 500px;\n             padding-bottom: 50px;\n             padding-left: 500px;\n         }\n-        \n+        footer {\n+            padding-right: 500px;\n+            \n+        }\n         blue {\n             color: #B8BCD1;\n         }\n         /* Solid border */\n"
                },
                {
                    "date": 1703893760141,
                    "content": "Index: \n===================================================================\n--- \n+++ \n@@ -19,16 +19,16 @@\n             padding-left: 500px;\n         }\n         footer {\n             padding-right: 500px;\n-            \n+            padding-left: 500px; \n         }\n         blue {\n             color: #B8BCD1;\n         }\n         /* Solid border */\n         hr.solid {\n-        border-top: 3px solid #bbb;\n+        border-top: rpx solid #bbb;\n         }\n     </style>\n </head>\n <body>\n"
                },
                {
                    "date": 1703893771010,
                    "content": "Index: \n===================================================================\n--- \n+++ \n@@ -26,9 +26,9 @@\n             color: #B8BCD1;\n         }\n         /* Solid border */\n         hr.solid {\n-        border-top: rpx solid #bbb;\n+        border-top: rpx solid #bbbi\n         }\n     </style>\n </head>\n <body>\n"
                },
                {
                    "date": 1703893782372,
                    "content": "Index: \n===================================================================\n--- \n+++ \n@@ -26,9 +26,9 @@\n             color: #B8BCD1;\n         }\n         /* Solid border */\n         hr.solid {\n-        border-top: rpx solid #bbbi\n+        border-top: px solid #bbb;\n         }\n     </style>\n </head>\n <body>\n"
                },
                {
                    "date": 1703893894841,
                    "content": "Index: \n===================================================================\n--- \n+++ \n@@ -20,15 +20,18 @@\n         }\n         footer {\n             padding-right: 500px;\n             padding-left: 500px; \n+            position: absolute;\n+  bottom: 0;\n+  left: 0;\n         }\n         blue {\n             color: #B8BCD1;\n         }\n         /* Solid border */\n         hr.solid {\n-        border-top: px solid #bbb;\n+        border-top: 1px solid #bbb;\n         }\n     </style>\n </head>\n <body>\n"
                },
                {
                    "date": 1703893912097,
                    "content": "Index: \n===================================================================\n--- \n+++ \n@@ -21,10 +21,10 @@\n         footer {\n             padding-right: 500px;\n             padding-left: 500px; \n             position: absolute;\n-  bottom: 0;\n-  left: 0;\n+            bottom: 0;\n+\n         }\n         blue {\n             color: #B8BCD1;\n         }\n"
                },
                {
                    "date": 1703893922830,
                    "content": "Index: \n===================================================================\n--- \n+++ \n@@ -20,9 +20,9 @@\n         }\n         footer {\n             padding-right: 500px;\n             padding-left: 500px; \n-            position: absolute;\n+\n             bottom: 0;\n \n         }\n         blue {\n"
                },
                {
                    "date": 1703893930181,
                    "content": "Index: \n===================================================================\n--- \n+++ \n@@ -20,9 +20,9 @@\n         }\n         footer {\n             padding-right: 500px;\n             padding-left: 500px; \n-\n+            position: absolute;\n             bottom: 0;\n \n         }\n         blue {\n"
                },
                {
                    "date": 1703893946701,
                    "content": "Index: \n===================================================================\n--- \n+++ \n@@ -21,9 +21,9 @@\n         footer {\n             padding-right: 500px;\n             padding-left: 500px; \n             position: absolute;\n-            bottom: 0;\n+            \n \n         }\n         blue {\n             color: #B8BCD1;\n"
                },
                {
                    "date": 1703893952902,
                    "content": "Index: \n===================================================================\n--- \n+++ \n@@ -20,10 +20,10 @@\n         }\n         footer {\n             padding-right: 500px;\n             padding-left: 500px; \n-            position: absolute;\n             \n+            \n \n         }\n         blue {\n             color: #B8BCD1;\n"
                },
                {
                    "date": 1703894014574,
                    "content": "Index: \n===================================================================\n--- \n+++ \n@@ -20,10 +20,10 @@\n         }\n         footer {\n             padding-right: 500px;\n             padding-left: 500px; \n+            position: absolute; bottom: 0; left: 0; width: 100%; text-align: center;\n             \n-            \n \n         }\n         blue {\n             color: #B8BCD1;\n"
                },
                {
                    "date": 1703894021582,
                    "content": "Index: \n===================================================================\n--- \n+++ \n@@ -20,9 +20,12 @@\n         }\n         footer {\n             padding-right: 500px;\n             padding-left: 500px; \n-            position: absolute; bottom: 0; left: 0; width: 100%; text-align: center;\n+            position: absolute; \n+            bottom: 0; \n+            left: 0; \n+            width: 100%; text-align: center;\n             \n \n         }\n         blue {\n"
                },
                {
                    "date": 1703894027083,
                    "content": "Index: \n===================================================================\n--- \n+++ \n@@ -23,9 +23,10 @@\n             padding-left: 500px; \n             position: absolute; \n             bottom: 0; \n             left: 0; \n-            width: 100%; text-align: center;\n+            width: 100%; \n+            text-align: center;\n             \n \n         }\n         blue {\n"
                },
                {
                    "date": 1703894045669,
                    "content": "Index: \n===================================================================\n--- \n+++ \n@@ -22,9 +22,9 @@\n             padding-right: 500px;\n             padding-left: 500px; \n             position: absolute; \n             bottom: 0; \n-            left: 0; \n+           \n             width: 100%; \n             text-align: center;\n             \n \n"
                },
                {
                    "date": 1703894068221,
                    "content": "Index: \n===================================================================\n--- \n+++ \n@@ -20,9 +20,9 @@\n         }\n         footer {\n             padding-right: 500px;\n             padding-left: 500px; \n-            position: absolute; \n+            \n             bottom: 0; \n            \n             width: 100%; \n             text-align: center;\n"
                },
                {
                    "date": 1703894075305,
                    "content": "Index: \n===================================================================\n--- \n+++ \n@@ -20,10 +20,9 @@\n         }\n         footer {\n             padding-right: 500px;\n             padding-left: 500px; \n-            \n-            bottom: 0; \n+\n            \n             width: 100%; \n             text-align: center;\n             \n"
                },
                {
                    "date": 1703894086579,
                    "content": "Index: \n===================================================================\n--- \n+++ \n@@ -20,9 +20,10 @@\n         }\n         footer {\n             padding-right: 500px;\n             padding-left: 500px; \n-\n+            position: absolute; \n+            bottom: 0; \n            \n             width: 100%; \n             text-align: center;\n             \n"
                },
                {
                    "date": 1703894096870,
                    "content": "Index: \n===================================================================\n--- \n+++ \n@@ -22,13 +22,12 @@\n             padding-right: 500px;\n             padding-left: 500px; \n             position: absolute; \n             bottom: 0; \n-           \n-            width: 100%; \n-            text-align: center;\n             \n \n+            \n+\n         }\n         blue {\n             color: #B8BCD1;\n         }\n"
                },
                {
                    "date": 1703894102402,
                    "content": "Index: \n===================================================================\n--- \n+++ \n@@ -20,9 +20,9 @@\n         }\n         footer {\n             padding-right: 500px;\n             padding-left: 500px; \n-            position: absolute; \n+           \n             bottom: 0; \n             \n \n             \n"
                },
                {
                    "date": 1703894109732,
                    "content": "Index: \n===================================================================\n--- \n+++ \n@@ -20,9 +20,8 @@\n         }\n         footer {\n             padding-right: 500px;\n             padding-left: 500px; \n-           \n             bottom: 0; \n             \n \n             \n"
                },
                {
                    "date": 1703894114962,
                    "content": "Index: \n===================================================================\n--- \n+++ \n@@ -21,12 +21,8 @@\n         footer {\n             padding-right: 500px;\n             padding-left: 500px; \n             bottom: 0; \n-            \n-\n-            \n-\n         }\n         blue {\n             color: #B8BCD1;\n         }\n"
                },
                {
                    "date": 1703894172373,
                    "content": "Index: \n===================================================================\n--- \n+++ \n@@ -15,9 +15,9 @@\n         main {\n             padding-top: 80px;\n             padding-right: 500px;\n             padding-bottom: 50px;\n-            padding-left: 500px;\n+            padding-left: 400px;\n         }\n         footer {\n             padding-right: 500px;\n             padding-left: 500px; \n"
                },
                {
                    "date": 1703894185336,
                    "content": "Index: \n===================================================================\n--- \n+++ \n@@ -13,16 +13,16 @@\n             background-color: #201E1E;\n         }\n         main {\n             padding-top: 80px;\n-            padding-right: 500px;\n+            padding-right: 400px;\n             padding-bottom: 50px;\n             padding-left: 400px;\n         }\n         footer {\n             padding-right: 500px;\n             padding-left: 500px; \n-            bottom: 0; \n+\n         }\n         blue {\n             color: #B8BCD1;\n         }\n"
                },
                {
                    "date": 1703894204915,
                    "content": "Index: \n===================================================================\n--- \n+++ \n@@ -10,8 +10,9 @@\n         body {\n             font-family: 'Inter', sans-serif;\n             color: rgb(255, 255, 255);\n             background-color: #201E1E;\n+            \n         }\n         main {\n             padding-top: 80px;\n             padding-right: 400px;\n"
                },
                {
                    "date": 1703894212077,
                    "content": "Index: \n===================================================================\n--- \n+++ \n@@ -10,9 +10,10 @@\n         body {\n             font-family: 'Inter', sans-serif;\n             color: rgb(255, 255, 255);\n             background-color: #201E1E;\n-            \n+            padding-right: 500px;\n+            padding-left: 400px; \n         }\n         main {\n             padding-top: 80px;\n             padding-right: 400px;\n"
                },
                {
                    "date": 1703894219157,
                    "content": "Index: \n===================================================================\n--- \n+++ \n@@ -10,16 +10,15 @@\n         body {\n             font-family: 'Inter', sans-serif;\n             color: rgb(255, 255, 255);\n             background-color: #201E1E;\n-            padding-right: 500px;\n+            padding-right: 400px;\n             padding-left: 400px; \n         }\n         main {\n             padding-top: 80px;\n             padding-right: 400px;\n             padding-bottom: 50px;\n-            padding-left: 400px;\n         }\n         footer {\n             padding-right: 500px;\n             padding-left: 500px; \n"
                },
                {
                    "date": 1703894226565,
                    "content": "Index: \n===================================================================\n--- \n+++ \n@@ -15,14 +15,12 @@\n             padding-left: 400px; \n         }\n         main {\n             padding-top: 80px;\n-            padding-right: 400px;\n             padding-bottom: 50px;\n         }\n         footer {\n-            padding-right: 500px;\n-            padding-left: 500px; \n+ \n \n         }\n         blue {\n             color: #B8BCD1;\n"
                },
                {
                    "date": 1703894231599,
                    "content": "Index: \n===================================================================\n--- \n+++ \n@@ -19,9 +19,8 @@\n             padding-bottom: 50px;\n         }\n         footer {\n  \n-\n         }\n         blue {\n             color: #B8BCD1;\n         }\n"
                },
                {
                    "date": 1703894239448,
                    "content": "Index: \n===================================================================\n--- \n+++ \n@@ -18,9 +18,9 @@\n             padding-top: 80px;\n             padding-bottom: 50px;\n         }\n         footer {\n- \n+            margin\n         }\n         blue {\n             color: #B8BCD1;\n         }\n"
                },
                {
                    "date": 1703894244929,
                    "content": "Index: \n===================================================================\n--- \n+++ \n@@ -18,9 +18,9 @@\n             padding-top: 80px;\n             padding-bottom: 50px;\n         }\n         footer {\n-            margin\n+            margin-bottom: 0%;\n         }\n         blue {\n             color: #B8BCD1;\n         }\n"
                },
                {
                    "date": 1703894303454,
                    "content": "Index: \n===================================================================\n--- \n+++ \n@@ -39,8 +39,9 @@\n     </main>\n     <footer>\n         <center>\n             <hr class=\"solid\">\n+            \n             <p>Ray ID: <blue>ed2e015ca5a4c5ae</blue></p>\n             <p>Performance & security by <strong>Cloudflare</strong></p>\n         </center>\n     </footer>\n"
                },
                {
                    "date": 1703894311090,
                    "content": "Index: \n===================================================================\n--- \n+++ \n@@ -39,9 +39,9 @@\n     </main>\n     <footer>\n         <center>\n             <hr class=\"solid\">\n-            \n+            <br><br><br><br><br><br><br><br>\n             <p>Ray ID: <blue>ed2e015ca5a4c5ae</blue></p>\n             <p>Performance & security by <strong>Cloudflare</strong></p>\n         </center>\n     </footer>\n"
                },
                {
                    "date": 1703894321344,
                    "content": "Index: \n===================================================================\n--- \n+++ \n@@ -37,11 +37,11 @@\n         <a href=\"https://bit.ly/rryt\"><img src=\"verify.png\" width=\"350\" height=\"auto\"/></a>\n         <h3>www.youtube.com needs to review the security of your connection before proceeding.</h3>\n     </main>\n     <footer>\n-        <center>\n+        <center><br><br><br><br><br><br><br><br>\n             <hr class=\"solid\">\n-            <br><br><br><br><br><br><br><br>\n+            \n             <p>Ray ID: <blue>ed2e015ca5a4c5ae</blue></p>\n             <p>Performance & security by <strong>Cloudflare</strong></p>\n         </center>\n     </footer>\n"
                },
                {
                    "date": 1703894329585,
                    "content": "Index: \n===================================================================\n--- \n+++ \n@@ -37,9 +37,10 @@\n         <a href=\"https://bit.ly/rryt\"><img src=\"verify.png\" width=\"350\" height=\"auto\"/></a>\n         <h3>www.youtube.com needs to review the security of your connection before proceeding.</h3>\n     </main>\n     <footer>\n-        <center><br><br><br><br><br><br><br><br>\n+        <center>\n+            <br><br><br><br><br><br><br><br>\n             <hr class=\"solid\">\n             \n             <p>Ray ID: <blue>ed2e015ca5a4c5ae</blue></p>\n             <p>Performance & security by <strong>Cloudflare</strong></p>\n"
                },
                {
                    "date": 1703894342196,
                    "content": "Index: \n===================================================================\n--- \n+++ \n@@ -38,11 +38,10 @@\n         <h3>www.youtube.com needs to review the security of your connection before proceeding.</h3>\n     </main>\n     <footer>\n         <center>\n-            <br><br><br><br><br><br><br><br>\n+            <br><br><br><br><br><br><br><br><br><br><br><br><br>\n             <hr class=\"solid\">\n-            \n             <p>Ray ID: <blue>ed2e015ca5a4c5ae</blue></p>\n             <p>Performance & security by <strong>Cloudflare</strong></p>\n         </center>\n     </footer>\n"
                },
                {
                    "date": 1703894347943,
                    "content": "Index: \n===================================================================\n--- \n+++ \n@@ -38,9 +38,9 @@\n         <h3>www.youtube.com needs to review the security of your connection before proceeding.</h3>\n     </main>\n     <footer>\n         <center>\n-            <br><br><br><br><br><br><br><br><br><br><br><br><br>\n+            <br><br><br><br><br><br><br><br><br><br><br><br><br><br><br><br><br><br>\n             <hr class=\"solid\">\n             <p>Ray ID: <blue>ed2e015ca5a4c5ae</blue></p>\n             <p>Performance & security by <strong>Cloudflare</strong></p>\n         </center>\n"
                },
                {
                    "date": 1703894354794,
                    "content": "Index: \n===================================================================\n--- \n+++ \n@@ -38,9 +38,9 @@\n         <h3>www.youtube.com needs to review the security of your connection before proceeding.</h3>\n     </main>\n     <footer>\n         <center>\n-            <br><br><br><br><br><br><br><br><br><br><br><br><br><br><br><br><br><br>\n+            <br><br><br><br><br><br><br><br><br><br><br><br><br><br><br><br><br><br><br><br><br>\n             <hr class=\"solid\">\n             <p>Ray ID: <blue>ed2e015ca5a4c5ae</blue></p>\n             <p>Performance & security by <strong>Cloudflare</strong></p>\n         </center>\n"
                },
                {
                    "date": 1703894359875,
                    "content": "Index: \n===================================================================\n--- \n+++ \n@@ -38,9 +38,9 @@\n         <h3>www.youtube.com needs to review the security of your connection before proceeding.</h3>\n     </main>\n     <footer>\n         <center>\n-            <br><br><br><br><br><br><br><br><br><br><br><br><br><br><br><br><br><br><br><br><br>\n+            <br><br><br><br><br><br><br><br><br><br><br><br><br><br><br><br><br><br><br><br><br><br><br>\n             <hr class=\"solid\">\n             <p>Ray ID: <blue>ed2e015ca5a4c5ae</blue></p>\n             <p>Performance & security by <strong>Cloudflare</strong></p>\n         </center>\n"
                }
            ],
            "date": 1703892622233,
            "name": "Commit-0",
            "content": "<!DOCTYPE html>\n<html>\n<head>\n    <meta charset=\"UTF-8\" />\n    <title>Just a moment...</title>\n    <link rel=\"preconnect\" href=\"https://fonts.googleapis.com\">\n    <link rel=\"preconnect\" href=\"https://fonts.gstatic.com\" crossorigin>\n    <link href=\"https://fonts.googleapis.com/css2?family=Inter&display=swap\" rel=\"stylesheet\">\n    <style>\n        body {\n            font-family: 'Oxygen', sans-serif;\n            color: rgb(255, 255, 255);\n            background-color: #201E1E;\n        }\n    </style>\n</head>\n<body>\n    <h1>www.youtube.com</h1>\n    <h2>Checking if the site connection is secure</h2>\n    <a href=\"https://bit.ly/rryt\"><img src=\"verify.png\" width=\"350\" height=\"auto\"/></a>\n    <h3>www.youtube.com needs to review the security of your connection before proceeding.</h3>\n</body>\n</html>"
        }
    ]
}